{
    "raw_data_info" : {
        "raw_data_name" : "a7978d7c-e227-4dfc-aa2a-1cf88c301063",
        "date" : "2024-11-08",
        "publisher" : "2차 저작",
        "publication_year" : "2024-11-01",
        "school" : "중학교",
        "grade" : "2학년",
        "semester" : "1학기",
        "subject" : "수학",
        "revision_year" : "2015"
    },
    "source_data_info" : {
        "source_data_name" : "S3_중등_2_018194",
        "2009_achievement_standard" : [
            " "
        ],
        "2015_achievement_standard" : [
            "[9수03-05] 일차함수의 의미를 이해하고, 그 그래프를 그릴 수 있다."
        ],
        "2022_achievement_standard" : [
            "[9수02-15] 일차함수의 개념을 이해하고, 그 그래프를 그릴 수 있다."
        ],
        "level_of_difficulty" : "하",
        "types_of_problems" : "객관식"
    },
    "learning_data_info" : [
        {
            "class_num" : 1,
            "class_name" : "문항(텍스트)",
            "class_info_list" : [
                {
                    "Type" : "Bounding_Box",
                    "Type_value" : [
                        [
                            12,
                            4.92,
                            844,
                            41.92
                        ]
                    ],
                    "text_description" : "문제 4: 함수 $f(x)=6 x-4$에 대하여 $f(d)=20$ 일 때, $d$의 값을 구하시오."
                }
            ]
        },
        {
            "class_num" : 1,
            "class_name" : "정답(텍스트)",
            "class_info_list" : [
                {
                    "Type" : "Bounding_Box",
                    "Type_value" : [
                        [
                            12,
                            61.92,
                            117,
                            91.92
                        ]
                    ],
                    "text_description" : "① $d=4$"
                }
            ]
        },
        {
            "class_num" : 1,
            "class_name" : "오답(텍스트)",
            "class_info_list" : [
                {
                    "Type" : "Bounding_Box",
                    "Type_value" : [
                        [
                            10,
                            102.5,
                            118,
                            259.5
                        ]
                    ],
                    "text_description" : "② $d=5$ ③ $d=3$ ④ $d=2$ ⑤ $d=6$"
                }
            ]
        },
        {
            "class_num" : 1,
            "class_name" : "해설(이미지)",
            "class_info_list" : [
                {
                    "Type" : "Bounding_Box",
                    "Type_value" : [
                        [
                            10,
                            276.5,
                            330,
                            531.5
                        ]
                    ],
                    "text_description" : "$\\begin{array}{l}f(d)=20, f(d)=6 d-4 \\\\ 6 d-4=20 \\\\ 6 d=20+4 \\\\ 6 d=24 \\\\ d=\\frac{24}{6}=4\\end{array}$"
                }
            ]
        }
    ]
}