{
    "raw_data_info" : {
        "raw_data_name" : "f6cc9041-4ccb-4064-a11d-24590d0f3905",
        "date" : "2024-11-08",
        "publisher" : "2차 저작",
        "publication_year" : "2024-11-01",
        "school" : "중학교",
        "grade" : "2학년",
        "semester" : "1학기",
        "subject" : "수학",
        "revision_year" : "2015"
    },
    "source_data_info" : {
        "source_data_name" : "S3_중등_2_018184",
        "2009_achievement_standard" : [
            " "
        ],
        "2015_achievement_standard" : [
            "[9수03-05] 일차함수의 의미를 이해하고, 그 그래프를 그릴 수 있다."
        ],
        "2022_achievement_standard" : [
            "[9수02-15] 일차함수의 개념을 이해하고, 그 그래프를 그릴 수 있다."
        ],
        "level_of_difficulty" : "하",
        "types_of_problems" : "객관식"
    },
    "learning_data_info" : [
        {
            "class_num" : 1,
            "class_name" : "문항(텍스트)",
            "class_info_list" : [
                {
                    "Type" : "Bounding_Box",
                    "Type_value" : [
                        [
                            96.14,
                            6.94,
                            830.27,
                            39.95
                        ]
                    ],
                    "text_description" : "함수 $f(x)=4 x+1$에 대하여 $f(d)=9$ 일 때, $d$의 값을 구하시오."
                }
            ]
        },
        {
            "class_num" : "1",
            "class_name" : "정답(이미지)",
            "class_info_list" : [
                {
                    "Type" : "Bounding_Box",
                    "Type_value" : [
                        [
                            13.18,
                            64.03,
                            116.65,
                            92.79
                        ]
                    ],
                    "text_description" : "① $d=2$"
                }
            ]
        },
        {
            "class_num" : 1,
            "class_name" : "오답(텍스트)",
            "class_info_list" : [
                {
                    "Type" : "Bounding_Box",
                    "Type_value" : [
                        [
                            11.39,
                            105.96,
                            139.85,
                            262.06
                        ]
                    ],
                    "text_description" : "② $d=1$ ③ $d=0$ ④ $d=4$ ⑤ $d=-2$"
                }
            ]
        },
        {
            "class_num" : "5",
            "class_name" : "해설(텍스트)",
            "class_info_list" : [
                {
                    "Type" : "Bounding_Box",
                    "Type_value" : [
                        [
                            4.26,
                            286.69,
                            304.87,
                            319.7
                        ]
                    ],
                    "text_description" : "$f(d)=9, f(d)=4 d+1$"
                },
                {
                    "Type" : "Bounding_Box",
                    "Type_value" : [
                        [
                            8.72,
                            339.32,
                            143.41,
                            372.33
                        ]
                    ],
                    "text_description" : "$4 d+1=9$"
                },
                {
                    "Type" : "Bounding_Box",
                    "Type_value" : [
                        [
                            4.26,
                            391.06,
                            139.85,
                            429.41
                        ]
                    ],
                    "text_description" : "$4 d=9-1$"
                },
                {
                    "Type" : "Bounding_Box",
                    "Type_value" : [
                        [
                            3.37,
                            448.15,
                            93.46,
                            480.26
                        ]
                    ],
                    "text_description" : "$4 d=8$"
                },
                {
                    "Type" : "Bounding_Box",
                    "Type_value" : [
                        [
                            3.37,
                            499.88,
                            133.6,
                            539.13
                        ]
                    ],
                    "text_description" : "$d=\\frac{8}{4}=2$"
                }
            ]
        }
    ]
}