{
    "raw_data_info" : {
        "raw_data_name" : "66a95de6-6ee4-48c4-9c64-8dcb49695166",
        "date" : "2024-11-08",
        "publisher" : "2차 저작",
        "publication_year" : "2024-11-01",
        "school" : "중학교",
        "grade" : "2학년",
        "semester" : "1학기",
        "subject" : "수학",
        "revision_year" : "2015"
    },
    "source_data_info" : {
        "source_data_name" : "S3_중등_2_017667",
        "2009_achievement_standard" : [
            " "
        ],
        "2015_achievement_standard" : [
            "[9수02-10] 일차부등식을 풀 수 있고, 이를 활용하여 문제를 해결할 수 있다."
        ],
        "2022_achievement_standard" : [
            "[9수02-12] 일차부등식을 풀 수 있고, 이를 활용하여 문제를 해결할 수 있다."
        ],
        "level_of_difficulty" : "하",
        "types_of_problems" : "객관식"
    },
    "learning_data_info" : [
        {
            "class_num" : 1,
            "class_name" : "문항(텍스트)",
            "class_info_list" : [
                {
                    "Type" : "Bounding_Box",
                    "Type_value" : [
                        [
                            16.28,
                            10.88,
                            255.64,
                            86.4
                        ]
                    ],
                    "text_description" : "다음 부등식을 푸시오. \\[ (3 x-7)>5 \\]"
                }
            ]
        },
        {
            "class_num" : 1,
            "class_name" : "정답(텍스트)",
            "class_info_list" : [
                {
                    "Type" : "Bounding_Box",
                    "Type_value" : [
                        [
                            15.64,
                            109.08,
                            120.6,
                            137.6
                        ]
                    ],
                    "text_description" : "① $x>4$"
                }
            ]
        },
        {
            "class_num" : 1,
            "class_name" : "오답(텍스트)",
            "class_info_list" : [
                {
                    "Type" : "Bounding_Box",
                    "Type_value" : [
                        [
                            16.28,
                            150.68,
                            119.32,
                            305.28
                        ]
                    ],
                    "text_description" : "② $x>2$ ③ $x \\geq 5$ ④ $x \\geq 3$ ⑤ $x<3$"
                }
            ]
        },
        {
            "class_num" : 1,
            "class_name" : "해설(이미지)",
            "class_info_list" : [
                {
                    "Type" : "Bounding_Box",
                    "Type_value" : [
                        [
                            24.6,
                            336.8,
                            160.92,
                            617.12
                        ]
                    ],
                    "text_description" : "$\\begin{array}{c}3 x-7>5 \\\\ 3 x>12 \\\\ \\\\ x>4\\end{array}$"
                }
            ]
        }
    ]
}